apodeixi/__init__.py
apodeixi/controllers/__init__.py
apodeixi/controllers/journeys/__init__.py
apodeixi/controllers/journeys/acceptance/__init__.py
apodeixi/controllers/journeys/acceptance/tests_unit/__init__.py
apodeixi/controllers/journeys/delivery_planning/__init__.py
apodeixi/controllers/journeys/delivery_planning/big_rocks.py
apodeixi/controllers/journeys/delivery_planning/tests_unit/__init__.py
apodeixi/controllers/journeys/delivery_planning/tests_unit/test_big_rocks.py
apodeixi/controllers/journeys/delivery_planning/tests_unit/input_data/simple_burnout_INPUT.xlsx
apodeixi/controllers/journeys/delivery_planning/tests_unit/output_data/saved_dict.yaml
apodeixi/controllers/journeys/delivery_planning/tests_unit/output_data/simple_burnout_big-rock-estimate_EXPECTED.yaml
apodeixi/controllers/journeys/delivery_planning/tests_unit/output_data/simple_burnout_big-rock-estimate_OUTPUT.yaml
apodeixi/controllers/journeys/delivery_planning/tests_unit/output_data/simple_burnout_big-rock_EXPECTED.yaml
apodeixi/controllers/journeys/delivery_planning/tests_unit/output_data/simple_burnout_big-rock_OUTPUT.yaml
apodeixi/controllers/journeys/delivery_planning/tests_unit/output_data/simple_burnout_explanations_EXPECTED.yaml
apodeixi/controllers/journeys/delivery_planning/tests_unit/output_data/simple_burnout_explanations_OUTPUT.yaml
apodeixi/controllers/journeys/delivery_planning/tests_unit/output_data/simple_burnout_investment_EXPECTED.yaml
apodeixi/controllers/journeys/delivery_planning/tests_unit/output_data/simple_burnout_investment_OUTPUT.yaml
apodeixi/controllers/journeys/delivery_planning/tests_unit/output_data/tmp.txt
apodeixi/controllers/journeys/funding/__init__.py
apodeixi/controllers/journeys/funding/tests_unit/__init__.py
apodeixi/controllers/kernel/__init__.py
apodeixi/controllers/kernel/bdd/__init__.py
apodeixi/controllers/kernel/bdd/capability_hierarchy.py
apodeixi/controllers/kernel/bdd/tests_unit/__init__.py
apodeixi-0.2.0a2.dist-info/LICENSE
apodeixi-0.2.0a2.dist-info/METADATA
apodeixi-0.2.0a2.dist-info/WHEEL
apodeixi-0.2.0a2.dist-info/top_level.txt
apodeixi-0.2.0a2.dist-info/RECORD
