Metadata-Version: 2.1
Name: apodeixi
Version: 0.2.0a2
Summary: Proof-oriented, reverse Conway domain model and controllers for human organizations, inspired by Kubernetes
Home-page: https://github.com/ChateauClaudia-Labs/apodeixi.git
Author: Alejandro Hernandez
Author-email: alejandro@chateauclaudia-labs.com
License: MIT
Project-URL: Bug Tracker, https://github.com/ChateauClaudia-Labs/apodeixi.git/issues
Platform: UNKNOWN
Classifier: Programming Language :: Python :: 3
Classifier: License :: OSI Approved :: MIT License
Classifier: Operating System :: OS Independent
Requires-Python: >=3.9
License-File: LICENSE
Requires-Dist: pandas (>=1.2.4)
Requires-Dist: openpyxl (>=3.0.7)
Requires-Dist: pyyaml (>=5.4.1)
Requires-Dist: xlsxwriter (>=1.3.8)
Requires-Dist: nltk (>=3.6.1)
